dashtext/__init__.py
dashtext/pydashtext.cpython-311-darwin.so
dashtext/version.py
dashtext/bm25/__init__.py
dashtext/bm25/bm25.py
dashtext/encoder/__init__.py
dashtext/encoder/sparse_vector_encoder.py
dashtext/hybrid/__init__.py
dashtext/hybrid/combine_dense_and_sparse.py
dashtext/tokenizer/__init__.py
dashtext/tokenizer/_base.py
dashtext/tokenizer/_jieba.py
dashtext/tokenizer/_stopwords.py
dashtext/tokenizer/auto.py
dashtext/tokenizer/data/stopwords.txt
dashtext/tokenizer/data/jieba/dict.txt
dashtext/tokenizer/data/jieba/dict.txt.big
dashtext/tokenizer/data/jieba/hmm_model.txt
dashtext/tokenizer/data/jieba/idf.txt.big
dashtext/tokenizer/data/jieba/stop_words.txt
dashtext/tokenizer/data/jieba/user_dict.txt
dashtext-0.0.7.dist-info/LICENSE.txt
dashtext-0.0.7.dist-info/METADATA
dashtext-0.0.7.dist-info/WHEEL
dashtext-0.0.7.dist-info/top_level.txt
dashtext-0.0.7.dist-info/RECORD
