Metadata-Version: 2.1
Name: dashtext
Version: 0.0.7
Summary: DashText is a Text Modal Data Library
Home-page: https://dashscope.aliyun.com/
Author: Alibaba
Author-email: dashvector@alibaba-inc.com
License: Apache 2.0
Platform: Posix; MacOS X; Windows
Classifier: Development Status :: 4 - Beta
Classifier: Intended Audience :: Developers
Classifier: License :: OSI Approved :: Apache Software License
Classifier: Programming Language :: Python
Classifier: Programming Language :: Python :: 3
Classifier: Programming Language :: Python :: 3.7
Classifier: Programming Language :: Python :: 3.8
Classifier: Programming Language :: Python :: 3.9
Classifier: Programming Language :: Python :: 3.10
Classifier: Programming Language :: Python :: 3.11
Requires-Python: >=3.7.0
License-File: LICENSE.txt
Requires-Dist: mmh3
Requires-Dist: numpy
